README.md
setup.py
cross_border_mover/__init__.py
cross_border_mover/alibabaScraper.py
cross_border_mover/amazonListing.py
cross_border_mover/downloader.py
cross_border_mover/driver1.py
cross_border_mover/eBayListing.py
cross_border_mover/imageToBase64.py
cross_border_mover/mover.py
cross_border_mover/pddScraper.py
cross_border_mover/taobaoScraper.py
cross_border_mover/wishListing.py
cross_border_mover.egg-info/PKG-INFO
cross_border_mover.egg-info/SOURCES.txt
cross_border_mover.egg-info/dependency_links.txt
cross_border_mover.egg-info/requires.txt
cross_border_mover.egg-info/top_level.txt