Metadata-Version: 2.1
Name: cross-border-mover
Version: 0.2.1
Summary: A Cross-border E-commerce Mover
Author: Zilu Chen
Author-email: 2822459649@qq.com
License: MIT
Keywords: E-commercei,Amazon,stable-diffusion
Requires-Python: >=3.11, <4
